amazon_bedrock_knowledge_base_mcp/__init__.py
amazon_bedrock_knowledge_base_mcp/__main__.py
amazon_bedrock_knowledge_base_mcp/server.py
amazon_bedrock_knowledge_base_mcp/app/__init__.py
amazon_bedrock_knowledge_base_mcp/app/factory.py
amazon_bedrock_knowledge_base_mcp/app/routes.py
amazon_bedrock_knowledge_base_mcp/app/service.py
amazon_bedrock_knowledge_base_mcp/auth/__init__.py
amazon_bedrock_knowledge_base_mcp/auth/auth0.py
amazon_bedrock_knowledge_base_mcp/aws/__init__.py
amazon_bedrock_knowledge_base_mcp/aws/bedrock_clients.py
amazon_bedrock_knowledge_base_mcp/aws/provider.py
amazon_bedrock_knowledge_base_mcp/core/__init__.py
amazon_bedrock_knowledge_base_mcp/core/config.py
amazon_bedrock_knowledge_base_mcp/core/logging.py
amazon_bedrock_knowledge_base_mcp/kb/__init__.py
amazon_bedrock_knowledge_base_mcp/kb/discovery.py
amazon_bedrock_knowledge_base_mcp/kb/filters.py
amazon_bedrock_knowledge_base_mcp/kb/models.py
amazon_bedrock_knowledge_base_mcp/kb/retrieval.py
amazon_bedrock_knowledge_base_mcp/kb/schema.py
amazon_bedrock_knowledge_base_mcp-0.1.1.dist-info/METADATA
amazon_bedrock_knowledge_base_mcp-0.1.1.dist-info/WHEEL
amazon_bedrock_knowledge_base_mcp-0.1.1.dist-info/entry_points.txt
amazon_bedrock_knowledge_base_mcp-0.1.1.dist-info/licenses/LICENSE
amazon_bedrock_knowledge_base_mcp-0.1.1.dist-info/licenses/NOTICE
amazon_bedrock_knowledge_base_mcp-0.1.1.dist-info/RECORD
