Metadata-Version: 2.4
Name: amazon-bedrock-knowledge-base-mcp
Version: 0.1.1
Summary: Standalone Model Context Protocol (MCP) server for Amazon Bedrock Knowledge Base Retrieval
Author: Zlash65
License: Apache-2.0
License-File: LICENSE
License-File: NOTICE
Classifier: License :: OSI Approved :: Apache Software License
Classifier: Operating System :: OS Independent
Classifier: Programming Language :: Python
Classifier: Programming Language :: Python :: 3
Classifier: Programming Language :: Python :: 3.10
Classifier: Programming Language :: Python :: 3.11
Classifier: Programming Language :: Python :: 3.12
Classifier: Programming Language :: Python :: 3.13
Requires-Python: >=3.10
Requires-Dist: boto3>=1.37.24
Requires-Dist: loguru>=0.7.3
Requires-Dist: mcp[cli]>=1.23.0
Requires-Dist: pydantic>=2.11.1
Requires-Dist: pyjwt[crypto]>=2.10.1
